borsdata_sdk/APIError.py
borsdata_sdk/BorsdataAPI.py
borsdata_sdk/__init__.py
borsdata_sdk/models/Branch.py
borsdata_sdk/models/Country.py
borsdata_sdk/models/Instrument.py
borsdata_sdk/models/InstrumentUpdate.py
borsdata_sdk/models/Market.py
borsdata_sdk/models/Report.py
borsdata_sdk/models/Sector.py
borsdata_sdk/models/StockPrice.py
borsdata_sdk/models/StockSplit.py
borsdata_sdk/models/__init__.py
borsdata_sdk/utils/__init__.py
borsdata_sdk/utils/transform.py
tests/__init__.py
tests/test_borsdataAPI.py
borsdata_sdk-1.2.1.dist-info/LICENSE
borsdata_sdk-1.2.1.dist-info/METADATA
borsdata_sdk-1.2.1.dist-info/WHEEL
borsdata_sdk-1.2.1.dist-info/top_level.txt
borsdata_sdk-1.2.1.dist-info/RECORD
