Metadata-Version: 2.1
Name: borsdata-sdk
Version: 1.2.1
Summary: Borsdata api SDK
Home-page: https://github.com/joelroxell/borsdata_sdk-sdk
Author: Joel S. Roxell
Author-email: joel.roxell@annevo.se
License: UNKNOWN
Platform: UNKNOWN
Classifier: Programming Language :: Python :: 3
Classifier: License :: OSI Approved :: MIT License
Classifier: Operating System :: OS Independent
Requires-Dist: requests
Requires-Dist: case-converter
